sphinxcontrib/__init__.py
sphinxcontrib/multilatex/__init__.py
sphinxcontrib/multilatex/builder.py
sphinxcontrib/multilatex/directive.py
sphinxcontrib_multilatex-0.1.3.dist-info/top_level.txt
sphinxcontrib_multilatex-0.1.3.dist-info/METADATA
sphinxcontrib_multilatex-0.1.3.dist-info/DESCRIPTION.rst
sphinxcontrib_multilatex-0.1.3.dist-info/metadata.json
sphinxcontrib_multilatex-0.1.3.dist-info/WHEEL
sphinxcontrib_multilatex-0.1.3.dist-info/RECORD
