Metadata-Version: 2.0
Name: sphinxcontrib-multilatex
Version: 0.1.3
Summary: Sphinx extension that allows LaTeX/PDF documents to be declared and parameterized within reStructuredText source files
Home-page: https://github.com/t4ngo/sphinxcontrib-multilatex
Author: Christo Butcher
Author-email: UNKNOWN
License: Apache 2.0
Platform: any
Classifier: Development Status :: 3 - Alpha
Classifier: Environment :: Other Environment
Classifier: Environment :: Plugins
Classifier: Framework :: Sphinx :: Extension
Classifier: Intended Audience :: Developers
Classifier: Intended Audience :: Information Technology
Classifier: Intended Audience :: Science/Research
Classifier: Intended Audience :: System Administrators
Classifier: License :: OSI Approved :: Apache Software License
Classifier: Natural Language :: English
Classifier: Operating System :: OS Independent
Classifier: Programming Language :: Python
Classifier: Topic :: Software Development :: Documentation
Classifier: Topic :: Software Development :: Libraries :: Python Modules
Requires-Dist: Sphinx (>=1.3)
